Ercarsng/__init__.py
Ercarsng/ercaspay.py
python_ercas_ng-1.0.0.dist-info/LICENCE
python_ercas_ng-1.0.0.dist-info/METADATA
python_ercas_ng-1.0.0.dist-info/WHEEL
python_ercas_ng-1.0.0.dist-info/top_level.txt
python_ercas_ng-1.0.0.dist-info/RECORD
