Metadata-Version: 2.1
Name: python_ercas_ng
Version: 1.0.0
Summary: This package simplifies ercasng payment processing in python
Home-page: https://github.com/amaechijude/ErcasPay
Author: Amaechi Ugwu
Author-email: amaechijude178@gmail.com
Classifier: Programming Language :: Python :: 3
Classifier: License :: OSI Approved :: MIT License
Classifier: Operating System :: OS Independent
Requires-Python: >=3.8
License-File: LICENCE
